ixnetwork_restpy/__init__.py
ixnetwork_restpy/base.py
ixnetwork_restpy/connection.py
ixnetwork_restpy/errors.py
ixnetwork_restpy/files.py
ixnetwork_restpy/multivalue.py
ixnetwork_restpy/steps.py
ixnetwork_restpy-1.0.3.dist-info/METADATA
ixnetwork_restpy-1.0.3.dist-info/RECORD
ixnetwork_restpy-1.0.3.dist-info/WHEEL
