Metadata-Version: 2.1
Name: ixnetwork_restpy
Version: 1.0.3
Summary: IxNetwork REST API Python Client
Home-page: https://keysight.com
Author: Keysight ISG IxNetwork team
Author-email: ixnetwork@keysight.com
License: MIT
Keywords: ixnetwork l2l3 test tool ixia automation
Platform: UNKNOWN
Classifier: Development Status :: 5 - Production/Stable
Classifier: Intended Audience :: Developers
Classifier: Topic :: Software Development
Classifier: License :: OSI Approved :: MIT License
Classifier: Programming Language :: Python :: 2.7
Classifier: Programming Language :: Python :: 3
